{"drwNo":"1128","drwNoDate":"2024-07-13","drwtNo1":"1","drwtNo2":"5","drwtNo3":"8","drwtNo4":"16","drwtNo5":"28","drwtNo6":"33","bnusNo":"45","totSellamnt":"111364194000","firstAccumamnt":"26455310280","firstPrzwnerCo":"63","firstWinamnt":"419925560","win_02_Accumamnt":"4409218429","win_02_PrzwnerCo":"77","win_02_Winamnt":"57262577","win_03_Accumamnt":"4409221219","win_03_PrzwnerCo":"2987","win_03_Winamnt":"1476137","win_04_Accumamnt":"7679600000","win_04_PrzwnerCo":"153592","win_04_Winamnt":"50000","win_05_Accumamnt":"12728750000","win_05_PrzwnerCo":"2545750","win_05_Winamnt":"5000","detail_info":""}