{"drwNo":"1153","drwNoDate":"2025-01-04","drwtNo1":"1","drwtNo2":"9","drwtNo3":"10","drwtNo4":"13","drwtNo5":"35","drwtNo6":"44","bnusNo":"5","totSellamnt":"126343367000","firstAccumamnt":"30409693875","firstPrzwnerCo":"15","firstWinamnt":"2027312925","win_02_Accumamnt":"5068282367","win_02_PrzwnerCo":"79","win_02_Winamnt":"64155473","win_03_Accumamnt":"5068284118","win_03_PrzwnerCo":"3506","win_03_Winamnt":"1445603","win_04_Accumamnt":"8384600000","win_04_PrzwnerCo":"167692","win_04_Winamnt":"50000","win_05_Accumamnt":"14240825000","win_05_PrzwnerCo":"2848165","win_05_Winamnt":"5000","detail_info":"(자동:11명, 수동:4명)"}