{"drwNo":"982","drwNoDate":"2021-09-25","drwtNo1":"5","drwtNo2":"7","drwtNo3":"13","drwtNo4":"20","drwtNo5":"21","drwtNo6":"44","bnusNo":"33","totSellamnt":"101344251000","firstAccumamnt":"24189045376","firstPrzwnerCo":"8","firstWinamnt":"3023630672","win_02_Accumamnt":"4031507619","win_02_PrzwnerCo":"81","win_02_Winamnt":"49771699","win_03_Accumamnt":"4031508432","win_03_PrzwnerCo":"2931","win_03_Winamnt":"1375472","win_04_Accumamnt":"6960400000","win_04_PrzwnerCo":"139208","win_04_Winamnt":"50000","win_05_Accumamnt":"11459665000","win_05_PrzwnerCo":"2291933","win_05_Winamnt":"5000","detail_info":"(자동:3명, 수동:4명, 반자동:1명)"}