{"bnusNo":"13","detail_info":"(자동:2명, 수동:1명, 반자동:1명)","drwNo":"733","drwNoDate":"2016-12-17","drwtNo1":"11","drwtNo2":"24","drwtNo3":"32","drwtNo4":"33","drwtNo5":"35","drwtNo6":"40","firstAccumamnt":"16066900500","firstPrzwnerCo":"4","firstWinamnt":"4016725125","totSellamnt":"69321488000","win_02_Accumamnt":"2677816794","win_02_PrzwnerCo":"57","win_02_Winamnt":"46979242","win_03_Accumamnt":"2677817824","win_03_PrzwnerCo":"1966","win_03_Winamnt":"1362064","win_04_Accumamnt":"5068450000","win_04_PrzwnerCo":"101369","win_04_Winamnt":"50000","win_05_Accumamnt":"8169760000","win_05_PrzwnerCo":"1633952","win_05_Winamnt":"5000"}