{"bnusNo":"26","detail_info":"","drwNo":"70","drwNoDate":"2004-04-03","drwtNo1":"5","drwtNo2":"19","drwtNo3":"22","drwtNo4":"25","drwtNo5":"28","drwtNo6":"43","firstAccumamnt":"15093833400","firstPrzwnerCo":"3","firstWinamnt":"5031277800","totSellamnt":"63232578000","win_02_Accumamnt":"2515637600","win_02_PrzwnerCo":"14","win_02_Winamnt":"179688400","win_03_Accumamnt":"2515594500","win_03_PrzwnerCo":"717","win_03_Winamnt":"3508500","win_04_Accumamnt":"5027962700","win_04_PrzwnerCo":"36781","win_04_Winamnt":"136700","win_05_Accumamnt":"6459900000","win_05_PrzwnerCo":"645990","win_05_Winamnt":"10000"}