{"bnusNo":"13","detail_info":"","drwNo":"248","drwNoDate":"2007-09-01","drwtNo1":"3","drwtNo2":"8","drwtNo3":"17","drwtNo4":"23","drwtNo5":"38","drwtNo6":"45","firstAccumamnt":"9819834904","firstPrzwnerCo":"8","firstWinamnt":"1227479363","totSellamnt":"42348403000","win_02_Accumamnt":"1636639152","win_02_PrzwnerCo":"23","win_02_Winamnt":"71158224","win_03_Accumamnt":"1636639620","win_03_PrzwnerCo":"1155","win_03_Winamnt":"1417004","win_04_Accumamnt":"3273305528","win_04_PrzwnerCo":"58847","win_04_Winamnt":"55624","win_05_Accumamnt":"4807810000","win_05_PrzwnerCo":"961562","win_05_Winamnt":"5000"}