{"bnusNo":"18","detail_info":"(자동:5명, 수동:2명)","drwNo":"371","drwNoDate":"2010-01-09","drwtNo1":"7","drwtNo2":"9","drwtNo3":"15","drwtNo4":"26","drwtNo5":"27","drwtNo6":"42","firstAccumamnt":"10668913801","firstPrzwnerCo":"7","firstWinamnt":"1524130543","totSellamnt":"45843166000","win_02_Accumamnt":"1778152313","win_02_PrzwnerCo":"29","win_02_Winamnt":"61315597","win_03_Accumamnt":"1778152560","win_03_PrzwnerCo":"1201","win_03_Winamnt":"1480560","win_04_Accumamnt":"3556333132","win_04_PrzwnerCo":"62102","win_04_Winamnt":"57266","win_05_Accumamnt":"5140060000","win_05_PrzwnerCo":"1028012","win_05_Winamnt":"5000"}