{"bnusNo":"27","detail_info":"","drwNo":"47","drwNoDate":"2003-10-25","drwtNo1":"14","drwtNo2":"17","drwtNo3":"26","drwtNo4":"31","drwtNo5":"36","drwtNo6":"45","firstAccumamnt":"16250212000","firstPrzwnerCo":"5","firstWinamnt":"3250042400","totSellamnt":"67756694000","win_02_Accumamnt":"2708368300","win_02_PrzwnerCo":"11","win_02_Winamnt":"246215300","win_03_Accumamnt":"2708345200","win_03_PrzwnerCo":"902","win_03_Winamnt":"3002600","win_04_Accumamnt":"5413372000","win_04_PrzwnerCo":"40580","win_04_Winamnt":"133400","win_05_Accumamnt":"6794660000","win_05_PrzwnerCo":"679466","win_05_Winamnt":"10000"}