{"bnusNo":"1","detail_info":"","drwNo":"171","drwNoDate":"2006-03-11","drwtNo1":"4","drwtNo2":"16","drwtNo3":"25","drwtNo4":"29","drwtNo5":"34","drwtNo6":"35","firstAccumamnt":"11768038200","firstPrzwnerCo":"6","firstWinamnt":"1961339700","totSellamnt":"50357474000","win_02_Accumamnt":"1961339714","win_02_PrzwnerCo":"19","win_02_Winamnt":"103228406","win_03_Accumamnt":"1961340392","win_03_PrzwnerCo":"1381","win_03_Winamnt":"1420232","win_04_Accumamnt":"3922708673","win_04_PrzwnerCo":"71461","win_04_Winamnt":"54893","win_05_Accumamnt":"5565340000","win_05_PrzwnerCo":"1113068","win_05_Winamnt":"5000"}