{"bnusNo":"42","detail_info":"(자동:6명, 수동:2명, 반자동:1명)","drwNo":"826","drwNoDate":"2018-09-29","drwtNo1":"13","drwtNo2":"16","drwtNo3":"24","drwtNo4":"25","drwtNo5":"33","drwtNo6":"36","firstAccumamnt":"18676728756","firstPrzwnerCo":"9","firstWinamnt":"2075192084","totSellamnt":"78218740000","win_02_Accumamnt":"3112788145","win_02_PrzwnerCo":"47","win_02_Winamnt":"66229535","win_03_Accumamnt":"3112789608","win_03_PrzwnerCo":"2232","win_03_Winamnt":"1394619","win_04_Accumamnt":"5431300000","win_04_PrzwnerCo":"108626","win_04_Winamnt":"50000","win_05_Accumamnt":"8775765000","win_05_PrzwnerCo":"1755153","win_05_Winamnt":"5000"}